{"name":null,"assets":"aoy4:pathy50:assets%2Fimages%2Fbackgrounds%2Fbackground_1-1.pngy4:sizei302y4:typey5:IMAGEy2:idR1goR0y50:assets%2Fimages%2Fbackgrounds%2Fbackground_1-2.pngR2i1168R3R4R5R6goR0y50:assets%2Fimages%2Fbackgrounds%2Fbackground_1-3.pngR2i1120R3R4R5R7goR0y40:assets%2Fimages%2Fplayer%2FMago.asepriteR2i622R3y6:BINARYR5R8goR0y40:assets%2Fimages%2Fplayer%2FMalo.asepriteR2i622R3R9R5R10goR0y35:assets%2Fimages%2Fplayer%2FMalo.pngR2i198R3R4R5R11goR0y38:assets%2Fimages%2Fplayer%2Funbrujo.pngR2i573R3R4R5R12goR0y24:assets%2Fmaps%2Festo.txtR2i29R3y4:TEXTR5R13goR0y43:assets%2Fsuper%20secret%2Fsuper%20secret.mdR2i107R3R14R5R15gh","rootPath":"../","version":2,"libraryArgs":[],"libraryType":null}